clargs/__about__.py
clargs/__init__.py
clargs/aap_from_data.py
clargs/clargs.py
clargs/docsparser.py
clargs/helper_types.py
clargs-0.9.0.dist-info/METADATA
clargs-0.9.0.dist-info/WHEEL
clargs-0.9.0.dist-info/licenses/LICENSE.txt
clargs-0.9.0.dist-info/RECORD
