Metadata-Version: 2.3
Name: clargs
Version: 0.9.0
Summary: Easily generate commandline apps from your functions, based on type hints
Project-URL: Documentation, https://github.com/reinhrst/clargs#readme
Project-URL: Issues, https://github.com/reinhrst/clargs/issues
Project-URL: Source, https://github.com/reinhrst/clargs
Author-email: Claude <pypi@claude.nl>
License-Expression: MIT
License-File: LICENSE.txt
Classifier: License :: OSI Approved :: MIT License
Classifier: Operating System :: OS Independent
Classifier: Programming Language :: Python
Classifier: Programming Language :: Python :: 3.10
Classifier: Programming Language :: Python :: 3.11
Classifier: Programming Language :: Python :: 3.12
Classifier: Programming Language :: Python :: Implementation :: CPython
Classifier: Programming Language :: Python :: Implementation :: PyPy
Requires-Python: >=3.10
